{"title":"멜론 티켓 ─ 단추TV","url":"https://ticket.melon.com/place/index.htm?placeId=1055","favicon":"https://ticket.melon.com/place/favicon.ico","elements":[{"title":"［온라인］노들섬 2주년 기획공연 〈The Wonder Weeks〉","contents":"2021.10.08  ~<br> 2021.11.14","link":"https://ticket.melon.com/performance/index.htm?prodId=206161","retrieved":1635610468676,"image":"https://cdnticket.melon.co.kr/resource/image/upload/product/2021/09/2021090614554473224830-8cbf-4216-9882-ce569641ab55.jpg/melon/resize/90x125/strip/true"}]}