{"title":"멜론 티켓 ─ 구름아래소극장","url":"https://ticket.melon.com/place/index.htm?placeId=724","favicon":"https://ticket.melon.com/place/favicon.ico","elements":[{"title":"유지애 2024 Fanmeeting［DELIGHT：여름비］","contents":"2024.07.27  ~<br> 2024.07.27","link":"https://ticket.melon.com/performance/index.htm?prodId=210084","retrieved":1721636347374,"image":"https://cdnticket.melon.co.kr/resource/image/upload/product/2024/07/202407031500532f926362-e8aa-4a99-9119-accd8bc13c9e.jpg/melon/resize/90x125/strip/true"}]}